MANIFEST.in
README.md
setup.py
./__init__.py
./workflows_create.py
./workflows_init.py
biowardrobe_cwl_workflows.egg-info/PKG-INFO
biowardrobe_cwl_workflows.egg-info/SOURCES.txt
biowardrobe_cwl_workflows.egg-info/dependency_links.txt
biowardrobe_cwl_workflows.egg-info/entry_points.txt
biowardrobe_cwl_workflows.egg-info/requires.txt
biowardrobe_cwl_workflows.egg-info/top_level.txt
biowardrobe_cwl_workflows.egg-info/zip-safe
expressiontools/fastqc-results-trigger.cwl
expressiontools/files-to-folder.cwl
expressiontools/get-file-by-name.cwl
metadata/chipseq-header.cwl
metadata/rnaseq-header.cwl
subworkflows/allele-alignreads-se-pe.cwl
subworkflows/allele-process-reference.cwl
subworkflows/allele-process-strain.cwl
subworkflows/allele-vcf-alignreads-se-pe.cwl
subworkflows/bam-bedgraph-bigwig.cwl
subworkflows/chipseq-gen-bigwig.cwl
subworkflows/heatmap-prepare.cwl
subworkflows/xenbase-fastq-bowtie-bigwig-se-pe.cwl
subworkflows/xenbase-sra-to-fastq-pe.cwl
subworkflows/xenbase-sra-to-fastq-se.cwl
tools/atdp.cwl
tools/bamtools-stats.cwl
tools/bedtools-genomecov.cwl
tools/bowtie-alignreads.cwl
tools/bowtie-build.cwl
tools/bowtie2-build.cwl
tools/bowtie2.cwl
tools/bzip2-compress.cwl
tools/crossmap.cwl
tools/custom-bash.cwl
tools/custom-bedops.cwl
tools/deseq-advanced.cwl
tools/extract-fastq.cwl
tools/fastq-dump.cwl
tools/fastqc.cwl
tools/fastx-quality-stats.cwl
tools/geep.cwl
tools/group-isoforms.cwl
tools/halliftover.cwl
tools/homer-annotate-peaks-hist.cwl
tools/homer-make-metagene-profile.cwl
tools/homer-make-tag-directory.cwl
tools/iaintersect.cwl
tools/linux-sort.cwl
tools/macs2-callpeak-biowardrobe-only.cwl
tools/macs2-callpeak.cwl
tools/macs2-island-count.cwl
tools/macs2-stat.cwl
tools/makegff.cwl
tools/picard-markduplicates.cwl
tools/plugin-plot-dna.cwl
tools/plugin-plot-rna.cwl
tools/python-get-stat-chipseq.cwl
tools/python-get-stat-rnaseq.cwl
tools/python-make-biowardrobe-isoforms.cwl
tools/reads-counting.cwl
tools/rename.cwl
tools/rose.cwl
tools/rsem-calculate-expression.cwl
tools/samtools-index.cwl
tools/samtools-merge.cwl
tools/samtools-rmdup.cwl
tools/samtools-sort-index.cwl
tools/samtools-sort.cwl
tools/samtools-view.cwl
tools/satscript.cwl
tools/split-heatmap.cwl
tools/star-alignreads.cwl
tools/star-genomegenerate.cwl
tools/trimgalore.cwl
tools/trimmomatic.cwl
tools/ucsc-bedgraphtobigwig.cwl
